pylint_ignore/__init__.py
pylint_ignore/__main__.py
pylint_ignore/ignorefile.py
pylint_ignore-2022.1025.dist-info/LICENSE
pylint_ignore-2022.1025.dist-info/METADATA
pylint_ignore-2022.1025.dist-info/WHEEL
pylint_ignore-2022.1025.dist-info/entry_points.txt
pylint_ignore-2022.1025.dist-info/top_level.txt
pylint_ignore-2022.1025.dist-info/zip-safe
pylint_ignore-2022.1025.dist-info/RECORD
