Metadata-Version: 2.1
Name: pylint-ignore
Version: 2022.1025
Summary: Start with silence, not with noise. But do start!
Home-page: https://github.com/mbarkhau/pylint-ignore
Author: Manuel Barkhau
Author-email: mbarkhau@gmail.com
License: MIT
Keywords: pylint ignore noise flake8 pep8 linter
Classifier: Development Status :: 4 - Beta
Classifier: Environment :: Console
Classifier: Environment :: Other Environment
Classifier: Intended Audience :: Developers
Classifier: License :: OSI Approved :: MIT License
Classifier: Operating System :: Unix
Classifier: Operating System :: POSIX
Classifier: Operating System :: MacOS :: MacOS X
Classifier: Operating System :: Microsoft :: Windows
Classifier: Programming Language :: Python
Classifier: Programming Language :: Python :: 3
Classifier: Programming Language :: Python :: Implementation :: CPython
Classifier: Programming Language :: Python :: Implementation :: PyPy
Classifier: Topic :: Software Development :: Libraries
Classifier: Topic :: Software Development :: Libraries :: Python Modules
Requires-Python: >=3.7
License-File: LICENSE
Requires-Dist: astroid (>2.1.0)
Requires-Dist: pylint (<2.13)
Requires-Dist: pathlib2
Requires-Dist: pylev
